{"BRAVIARY": {"pokemon": "Braviary", "stone": "Braviarita", "stoneInternal": "BRAVIARITA"}, "KINGLER": {"pokemon": "Kingler", "stone": "Kinglerita", "stoneInternal": "KINGLERITA"}, "BUTTERFREE": {"pokemon": "Butterfree", "stone": "Butterfreeita", "stoneInternal": "BUTTERFREEITA"}, "MACHAMP": {"pokemon": "Machamp", "stone": "Machampita", "stoneInternal": "MACHAMPITA"}, "LAPRAS": {"pokemon": "Lapras", "stone": "Laprasita", "stoneInternal": "LAPRASITA"}, "GARBODOR": {"pokemon": "Garbodor", "stone": "Garbodorita", "stoneInternal": "GARBODORITA"}, "CORVINIGHT": {"pokemon": "Corvinight", "stone": "Corvinightita", "stoneInternal": "CORVIKNIGHTITA"}, "ORBEETLE": {"pokemon": "Orbeetle", "stone": "Orbeetleita", "stoneInternal": "ORBEETLEITA"}, "DREDNAW": {"pokemon": "Drednaw", "stone": "Drednawita", "stoneInternal": "DREDNAWITA"}, "COALOSSAL": {"pokemon": "Coalossal", "stone": "Coalossalita", "stoneInternal": "COALOSSALITA"}, "FLAPPLE": {"pokemon": "Flapple", "stone": "Megapiedra Manzánida", "stoneInternal": "FLAPPLETUNITA"}, "SANDACONDA": {"pokemon": "Sandaconda", "stone": "Sandacondita", "stoneInternal": "SANDACONDITA"}, "TOXTRICITY": {"pokemon": "Toxtricity", "stone": "Toxtricitita", "stoneInternal": "TOXTRICITITA"}, "CENTISKORCH": {"pokemon": "Centiskorch", "stone": "Centiskorchita", "stoneInternal": "CENTISKORCHITA"}, "HATTERENE": {"pokemon": "Hatterene", "stone": "Hatterenita", "stoneInternal": "HATTERENITA"}, "GRIMMSNARL": {"pokemon": "Grimmsnarl", "stone": "Grimmsnarlita", "stoneInternal": "GRIMMSNARLITA"}, "ALCREMIE": {"pokemon": "Alcremie", "stone": "Alcremita", "stoneInternal": "ALCREMITA"}, "COPPERAJAH": {"pokemon": "Copperajah", "stone": "Copperajita", "stoneInternal": "COPPERAJITA"}, "DURALUDON": {"pokemon": "Duraludon", "stone": "Duraludonita", "stoneInternal": "DURALUDONITA"}, "ALAKAZAM": {"pokemon": "Alakazam", "stone": "Alakazamita", "stoneInternal": "ALAKAZAMITA"}, "GENGAR": {"pokemon": "Gengar", "stone": "Gengarita", "stoneInternal": "GENGARITA"}, "KANGASKHAN": {"pokemon": "Kangaskhan", "stone": "Kangaskhanita", "stoneInternal": "KANGASKHANITA"}, "PINSIR": {"pokemon": "Pinsir", "stone": "Pinsirita", "stoneInternal": "PINSIRITA"}, "GYARADOS": {"pokemon": "Gyarados", "stone": "Gyaradosita", "stoneInternal": "GYARADOSITA"}, "AERODACTYL": {"pokemon": "Aerodactyl", "stone": "Aerodactylita", "stoneInternal": "AERODACTYLITA"}, "AMPHAROS": {"pokemon": "Ampharos", "stone": "Ampharosita", "stoneInternal": "AMPHAROSITA"}, "SCIZOR": {"pokemon": "Scizor", "stone": "Scizorita", "stoneInternal": "SCIZORITA"}, "HERACROSS": {"pokemon": "Heracross", "stone": "Heracrossita", "stoneInternal": "HERACROSSITA"}, "HOUNDOOM": {"pokemon": "Houndoom", "stone": "Houndoomita", "stoneInternal": "HOUNDOOMITA"}, "GARDEVOIR": {"pokemon": "Gardevoir", "stone": "Gardevoirita", "stoneInternal": "GARDEVOIRITA"}, "AGGRON": {"pokemon": "Aggron", "stone": "Aggronita", "stoneInternal": "AGGRONITA"}, "MEDICHAM": {"pokemon": "Medicham", "stone": "Medichamita", "stoneInternal": "MEDICHAMITA"}, "MANECTRIC": {"pokemon": "Manectric", "stone": "Manectrita", "stoneInternal": "MANECTRITA"}, "ABSOL": {"pokemon": "Absol", "stone": "Absolita Z", "stoneInternal": "ABSOLITEZ"}, "LUCARIO": {"pokemon": "Lucario", "stone": "Lucarionita Z", "stoneInternal": "LUCARIONITEZ"}, "BEEDRILL": {"pokemon": "Beedrill", "stone": "Beedrillita", "stoneInternal": "BEEDRILLITA"}, "PIDGEOT": {"pokemon": "Pidgeot", "stone": "Pidgeotita", "stoneInternal": "PIDGEOTITA"}, "SLOWBRO": {"pokemon": "Slowbro", "stone": "Slowbrita", "stoneInternal": "SLOWBRITA"}, "STEELIX": {"pokemon": "Steelix", "stone": "Steelixita", "stoneInternal": "STEELIXITA"}, "SABLEYE": {"pokemon": "Sableye", "stone": "Sableyita", "stoneInternal": "SABLEYITA"}, "SHARPEDO": {"pokemon": "Sharpedo", "stone": "Sharpedita", "stoneInternal": "SHARPEDITA"}, "CAMERUPT": {"pokemon": "Camerupt", "stone": "Cameruptita", "stoneInternal": "CAMERUPTITA"}, "ALTARIA": {"pokemon": "Altaria", "stone": "Altarita", "stoneInternal": "ALTARITA"}, "GLALIE": {"pokemon": "Glalie", "stone": "Glalieita", "stoneInternal": "GLALIEITA"}, "GALLADE": {"pokemon": "Gallade", "stone": "Galladita", "stoneInternal": "GALLADITA"}, "TUS POKÉMON USANDO MEGAPIEDRAS": {"pokemon": "tus Pokémon usando megapiedras", "stone": "Megaevolución", "stoneInternal": "BRAZALESPIRITUAL"}, "SEVIPER": {"pokemon": "Seviper", "stone": "Seviperita", "stoneInternal": "SEVIPERITA"}, "GASTESLA": {"pokemon": "Gastesla", "stone": "Gasteslita", "stoneInternal": "GASTESLITA"}, "LUNAYE": {"pokemon": "Lunaye", "stone": "Lunayita", "stoneInternal": "LUNAYITA"}, "NARVALOR": {"pokemon": "Narvalor", "stone": "Narvalorita", "stoneInternal": "NARVALORITA"}, "GRENINJA": {"pokemon": "Greninja", "stone": "Greninjita", "stoneInternal": "GRENINJITA"}, "BLAZIKEN": {"pokemon": "Blaziken", "stone": "Blazikenita", "stoneInternal": "BLAZIKENITE"}, "PIKACHU": {"pokemon": "Pikachu", "stone": "Pikachuita", "stoneInternal": "PIKACHUITA"}, "VENUSAUR": {"pokemon": "Venusaur", "stone": "Venusaurita", "stoneInternal": "VENUSAURITE"}, "CHARIZARD": {"pokemon": "Charizard", "stone": "Charizardita X", "stoneInternal": "CHARIZARDITEX"}, "BLASTOISE": {"pokemon": "Blastoise", "stone": "Blastoisita", "stoneInternal": "BLASTOISINITE"}, "TYRANITAR": {"pokemon": "Tyranitar", "stone": "Tyranita", "stoneInternal": "TYRANITARITE"}, "SCEPTILE": {"pokemon": "Sceptile", "stone": "Sceptilita", "stoneInternal": "SCEPTILITE"}, "SWAMPERT": {"pokemon": "Swampert", "stone": "Swampertita", "stoneInternal": "SWAMPERTITE"}, "SALAMENCE": {"pokemon": "Salamence", "stone": "Salamencita", "stoneInternal": "SALAMENCITE"}, "METAGROSS": {"pokemon": "Metagross", "stone": "Metagrossita", "stoneInternal": "METAGROSSITE"}, "GARCHOMP": {"pokemon": "Garchomp", "stone": "Garchompita Z", "stoneInternal": "GARCHOMPITEZ"}, "LOPUNNY": {"pokemon": "Lopunny", "stone": "Lopunnyta", "stoneInternal": "LOPUNNYTE"}, "FLORGES": {"pokemon": "Florges", "stone": "Florgesita", "stoneInternal": "FLORGESITA"}, "RAYQUAZA": {"pokemon": "Rayquaza", "stone": "Rayquazita", "stoneInternal": "RAYQUAZITE"}, "ABOMASNOW": {"pokemon": "Abomasnow", "stone": "Abomasnowita", "stoneInternal": "ABOMASNOWITA"}, "DIANCIE": {"pokemon": "Diancie", "stone": "Diancita", "stoneInternal": "DIANCITA"}, "CHESNAUGHT": {"pokemon": "Chesnaught", "stone": "Chesnaughtita", "stoneInternal": "CHESNAUGHTITA"}, "DELPHOX": {"pokemon": "Delphox", "stone": "Delphoxita", "stoneInternal": "DELPHOXITA"}, "RILLABOOM": {"pokemon": "Rillaboom", "stone": "Rillaboomita", "stoneInternal": "RILLABOOMITA"}, "CINDERACE": {"pokemon": "Cinderace", "stone": "Cinderacita", "stoneInternal": "CINDERACITA"}, "INTELEON": {"pokemon": "Inteleon", "stone": "Inteleonita", "stoneInternal": "INTELEONITA"}, "ZYGARDE": {"pokemon": "Zygarde", "stone": "Zygardita", "stoneInternal": "ZYGARDITA"}, "ENTEI": {"pokemon": "Entei", "stone": "Enteita", "stoneInternal": "ENTEITA"}, "FLOETTE": {"pokemon": "Floette", "stone": "Floettita", "stoneInternal": "FLOETTITA"}, "VOLCARONA": {"pokemon": "Volcarona", "stone": "Volcaronita", "stoneInternal": "VOLCARONITA"}, "DRAMPA": {"pokemon": "Drampa", "stone": "Drampita", "stoneInternal": "DRAMPANITE"}, "VICTREEBEL": {"pokemon": "Victreebel", "stone": "Victreebelita", "stoneInternal": "VICTREEBELITE"}, "DRAGONITE": {"pokemon": "Dragonite", "stone": "Dragonitita", "stoneInternal": "DRAGONINITE"}, "MALAMAR": {"pokemon": "Malamar", "stone": "Malamarita", "stoneInternal": "MALAMARITE"}, "HAWLUCHA": {"pokemon": "Hawlucha", "stone": "Hawluchita", "stoneInternal": "HAWLUCHANITE"}, "CLEFABLE": {"pokemon": "Clefable", "stone": "Clefablita", "stoneInternal": "CLEFABLITE"}, "STARMIE": {"pokemon": "Starmie", "stone": "Starmita", "stoneInternal": "STARMINITE"}, "MEGANIUM": {"pokemon": "Meganium", "stone": "Meganiumita", "stoneInternal": "MEGANIUMITE"}, "FERALIGATR": {"pokemon": "Feraligatr", "stone": "Feraligatrita", "stoneInternal": "FERALIGITE"}, "SKARMORY": {"pokemon": "Skarmory", "stone": "Skarmorita", "stoneInternal": "SKARMORITE"}, "FROSLASS": {"pokemon": "Froslass", "stone": "Froslassita", "stoneInternal": "FROSLASSITE"}, "EMBOAR": {"pokemon": "Emboar", "stone": "Emboarita", "stoneInternal": "EMBOARITE"}, "EXCADRILL": {"pokemon": "Excadrill", "stone": "Excadrillita", "stoneInternal": "EXCADRITE"}, "SCOLIPEDE": {"pokemon": "Scolipede", "stone": "Scolipedita", "stoneInternal": "SCOLIPITE"}, "SCRAFTY": {"pokemon": "Scrafty", "stone": "Scraftita", "stoneInternal": "SCRAFTINITE"}, "EELEKTROSS": {"pokemon": "Eelektross", "stone": "Eelektrossita", "stoneInternal": "EELEKTROSSITE"}, "CHANDELURE": {"pokemon": "Chandelure", "stone": "Chandelurita", "stoneInternal": "CHANDELURITE"}, "PYROAR": {"pokemon": "Pyroar", "stone": "Pyroarita", "stoneInternal": "PYROARITE"}, "BARBARACLE": {"pokemon": "Barbaracle", "stone": "Barbaraclita", "stoneInternal": "BARBARACITE"}, "DRAGALGE": {"pokemon": "Dragalge", "stone": "Dragalgita", "stoneInternal": "DRAGALGITE"}, "FALINKS": {"pokemon": "Falinks", "stone": "Falinksita", "stoneInternal": "FALINKSITE"}, "RAICHU": {"pokemon": "Raichu", "stone": "Raichuita", "stoneInternal": "RAICHUITE"}, "CHIMECHO": {"pokemon": "Chimecho", "stone": "Chimechita", "stoneInternal": "CHIMECHITE"}, "STARAPTOR": {"pokemon": "Staraptor", "stone": "Staraptita", "stoneInternal": "STARAPTITE"}, "GOLURK": {"pokemon": "Golurk", "stone": "Golurkita", "stoneInternal": "GOLURKITE"}, "MEOWSTIC": {"pokemon": "Meowstic", "stone": "Meowsticita", "stoneInternal": "MEOWSTICITE"}, "CRABOMINABLE": {"pokemon": "Crabominable", "stone": "Crabominita", "stoneInternal": "CRABOMINITE"}, "GOLISOPOD": {"pokemon": "Golisopod", "stone": "Golisopita", "stoneInternal": "GOLISOPITE"}, "MAGEARNA": {"pokemon": "Magearna", "stone": "Magearnita", "stoneInternal": "MAGEARNITE"}, "SCOVILLAIN": {"pokemon": "Scovillain", "stone": "Scovillainita", "stoneInternal": "SCOVILLAINITE"}, "BAXCALIBUR": {"pokemon": "Baxcalibur", "stone": "Baxcalibrita", "stoneInternal": "BAXCALIBRITE"}, "TATSUGIRI": {"pokemon": "Tatsugiri", "stone": "Tatsugirinita", "stoneInternal": "TATSUGIRINITE"}, "GLIMMORA": {"pokemon": "Glimmora", "stone": "Glimmoranita", "stoneInternal": "GLIMMORANITE"}, "HEATRAN": {"pokemon": "Heatran", "stone": "Heatranita", "stoneInternal": "HEATRANITE"}, "DARKRAI": {"pokemon": "Darkrai", "stone": "Darkranita", "stoneInternal": "DARKRANITE"}, "ZERAORA": {"pokemon": "Zeraora", "stone": "Zeraorita", "stoneInternal": "ZERAORITE"}}